onpolicy/__init__.py
onpolicy/foo.py
onpolicy-0.0.1.dist-info/LICENSE
onpolicy-0.0.1.dist-info/METADATA
onpolicy-0.0.1.dist-info/WHEEL
onpolicy-0.0.1.dist-info/RECORD
