Metadata-Version: 2.1
Name: onpolicy
Version: 0.0.1
Summary: On-policy training made easy
Home-page: https://github.com/AlgoDistill/onpolicy
Author: Algo Distill
Author-email: algoDistill@protonmail.com
Requires-Python: >=3.8,<4.0
Classifier: Programming Language :: Python :: 3
Classifier: Programming Language :: Python :: 3.8
Classifier: Programming Language :: Python :: 3.9
Classifier: Programming Language :: Python :: 3.10
Classifier: Programming Language :: Python :: 3.11
Classifier: Programming Language :: Python :: 3.12
Project-URL: Documentation, https://AlgoDistill.github.io/onpolicy/
Project-URL: Repository, https://github.com/AlgoDistill/onpolicy
